AUTHORS.rst
CONTRIBUTING.rst
LICENSE
MANIFEST.in
README.rst
setup.cfg
setup.py
djangocms_fbcomments/__init__.py
djangocms_fbcomments/cms_plugins.py
djangocms_fbcomments/conf.py
djangocms_fbcomments/models.py
djangocms_fbcomments.egg-info/PKG-INFO
djangocms_fbcomments.egg-info/SOURCES.txt
djangocms_fbcomments.egg-info/dependency_links.txt
djangocms_fbcomments.egg-info/not-zip-safe
djangocms_fbcomments.egg-info/requires.txt
djangocms_fbcomments.egg-info/top_level.txt
djangocms_fbcomments/migrations/0001_initial.py
djangocms_fbcomments/migrations/__init__.py
djangocms_fbcomments/south_migrations/0001_initial.py
djangocms_fbcomments/south_migrations/__init__.py
djangocms_fbcomments/static/css/djangocms_fbcomments/admin/djangocms_fbcomments.css
djangocms_fbcomments/static/js/djangocms_fbcomments/jquery.fbcomments.js
djangocms_fbcomments/static/js/djangocms_fbcomments/jquery.lazyload.js
djangocms_fbcomments/static/js/djangocms_fbcomments/admin/djangocms_fbcomments.js
djangocms_fbcomments/templates/djangocms_fbcomments/default.html