Metadata-Version: 1.1
Name: djangocms-fbcomments
Version: 0.1.1
Summary: The easiest way to integrate Facebook Comments for your django-cms powered site with lazy-loading, analytics and more.
Home-page: https://github.com/mishbahr/djangocms-fbcomments
Author: Mishbah Razzaque
Author-email: mishbahx@gmail.com
License: BSD
Keywords: djangocms-fbcomments,facebook,django-cms,cmsplugin-fbcomments
Platform: UNKNOWN
Classifier: Development Status :: 4 - Beta
Classifier: Framework :: Django
Classifier: Intended Audience :: Developers
Classifier: License :: OSI Approved :: BSD License
Classifier: Natural Language :: English
Classifier: Programming Language :: Python :: 2
Classifier: Programming Language :: Python :: 2.7
Classifier: Programming Language :: Python :: 3
Classifier: Programming Language :: Python :: 3.3
Classifier: Programming Language :: Python :: 3.4
